{
  "actions": {
    "name": "Actions",
    "description": "Components that trigger an action.",
    "items": ["Button", "Icon Button"],
    "next": [],
    "new": [],
    "deprecated": []
  },
  "communication": {
    "name": "Communication",
    "description": "Communication components provide useful information.",
    "items": [
      "Admonition",
      "Accordion",
      "Avatar",
      "Notifications",
      "Progress Indicators",
      "Tag",
      "Tooltip"
    ],
    "next": [],
    "new": [],
    "deprecated": []
  },
  "containment": {
    "name": "Containment",
    "description": "Components that contain other components.",
    "items": [
      "Confirm Modal",
      "Prompt Modal",
      "CTA Modal",
      "Modal",
      "Dialog",
      "Table"
    ],
    "next": [],
    "new": [],
    "deprecated": ["Modal"]
  },
  "navigation": {
    "name": "Navigation",
    "description": "Components that help users navigate through the app.",
    "items": ["Menu", "Tabs"],
    "next": [],
    "new": [],
    "deprecated": []
  },
  "selection": {
    "name": "Selection",
    "description": "Components that allow users to select choices.",
    "items": [
      "Drag & Drop",
      "Checkbox",
      "Date Picker",
      "Radio",
      "Rating",
      "Select",
      "Combobox",
      "Switch"
    ],
    "next": [],
    "new": [],
    "deprecated": []
  },
  "inputs": {
    "name": "Inputs",
    "description": "Components that allow users to input data.",
    "items": [
      "Field",
      "Input",
      "Textarea",
      "Label",
      "Fieldset",
      "Field Message",
      "File Uploader"
    ],
    "next": [],
    "new": [],
    "deprecated": ["Label", "Field Message"]
  }
}
